acfile/__init__.py
acfile/acf.py
acfile/read.py
acfile/section.py
acfile-0.2.3.dist-info/LICENSE
acfile-0.2.3.dist-info/METADATA
acfile-0.2.3.dist-info/WHEEL
acfile-0.2.3.dist-info/top_level.txt
acfile-0.2.3.dist-info/RECORD
